dftp/__init__.py
dftp/app.py
dftp-0.3.dist-info/LICENSE
dftp-0.3.dist-info/METADATA
dftp-0.3.dist-info/WHEEL
dftp-0.3.dist-info/entry_points.txt
dftp-0.3.dist-info/top_level.txt
dftp-0.3.dist-info/RECORD
