Metadata-Version: 2.1
Name: dftp
Version: 0.3
Summary: Command-line interface for Remember the Milk.
Home-page: https://codeberg.org/kdwarn/dont-forget-the-python
Author: Kris Warner
Author-email: kdwarn@protonmail.com
Classifier: Programming Language :: Python :: 3
Classifier: License :: OSI Approved :: MIT License
Classifier: Operating System :: OS Independent
License-File: LICENSE
Requires-Dist: click (>=6.7)
Requires-Dist: requests (>=2.19.1)
Requires-Dist: arrow (>=0.12.1)
Requires-Dist: reportlab (>=3.5.2)
Requires-Dist: tabulate (>=0.8.2)
